[
  {
    "device": "openaps://raspberrypi", 
    "created_at": "2016-07-07T08:31:45.614Z", 
    "pump": {
      "battery": {
        "status": "normal", 
        "voltage": 1.29
      }, 
      "status": {
        "status": "normal", 
        "timestamp": "2016-07-07T08:31:23.000Z", 
        "bolusing": false, 
        "suspended": false
      }, 
      "reservoir": 131.7, 
      "clock": "2016-07-07T01:31:08-07:00"
    }, 
    "_id": "577e13714966ceb853e10c3c", 
    "openaps": {
      "suggested": {
        "bg": 157, 
        "temp": "absolute", 
        "snoozeBG": 299, 
        "timestamp": "2016-07-07T08:17:09.000Z", 
        "reason": "Eventual BG -37<125, but Avg. Delta 10.00 > Exp. Delta 3.2; setting current basal of 1.5 as temp. Setting neutral temp basal of 1.5U/hr", 
        "rate": 1.5, 
        "eventualBG": -37, 
        "duration": 30, 
        "mealAssist": "Off: Carbs: undefined Boluses: undefined ISF: 25, Target: 130 Deviation: 34 BGI: -1.41", 
        "tick": "+10"
      }, 
      "iob": {
        "netbasalinsulin": 0, 
        "timestamp": "2016-07-07T08:30:55.000Z", 
        "activity": 0.0317, 
        "basaliob": 0, 
        "hightempinsulin": 0, 
        "bolussnooze": 7.563, 
        "iob": 8.751
      }, 
      "enacted": {
        "bg": 157, 
        "temp": "absolute", 
        "snoozeBG": 299, 
        "recieved": true, 
        "rate": 1.5, 
        "reason": "Eventual BG -37<125, but Avg. Delta 10.00 > Exp. Delta 3.2; setting current basal of 1.5 as temp. Setting neutral temp basal of 1.5U/hr", 
        "eventualBG": -37, 
        "timestamp": "2016-07-07T08:17:28.000Z", 
        "duration": 30, 
        "mealAssist": "Off: Carbs: undefined Boluses: undefined ISF: 25, Target: 130 Deviation: 34 BGI: -1.41", 
        "tick": "+10"
      }
    }
  }
]