[
  {
    "device": "openaps://raspberrypi", 
    "created_at": "2016-07-07T09:56:58.878Z", 
    "pump": {
      "battery": {
        "status": "normal", 
        "voltage": 1.28
      }, 
      "status": {
        "status": "normal", 
        "timestamp": "2016-07-07T09:56:29.000Z", 
        "bolusing": false, 
        "suspended": true
      }, 
      "reservoir": 131, 
      "clock": "2016-07-07T02:56:14-07:00"
    }, 
    "_id": "577e276a4966ceb853e10c64", 
    "openaps": {
      "suggested": {
        "bg": 95, 
        "temp": "absolute", 
        "snoozeBG": 52, 
        "timestamp": "2016-07-07T09:52:08.000Z", 
        "reason": "Eventual BG 52<125, Snooze BG 52, setting -10.92U/hr", 
        "rate": 0, 
        "eventualBG": 52, 
        "duration": 30, 
        "mealAssist": "Off: Carbs: undefined Boluses: undefined ISF: 25, Target: 130 Deviation: 7 BGI: -8.86", 
        "tick": -6
      }, 
      "iob": {
        "netbasalinsulin": -0.75, 
        "timestamp": "2016-07-07T09:55:55.000Z", 
        "activity": 0.0654, 
        "basaliob": -0.648, 
        "hightempinsulin": 0, 
        "bolussnooze": 0, 
        "iob": 1.683
      }, 
      "enacted": {
        "requested": {
          "duration": 30, 
          "rate": 0, 
          "temp": "absolute"
        }, 
        "bg": 95, 
        "temp": "absolute", 
        "snoozeBG": 52, 
        "timestamp": "2016-07-07T09:52:27.000Z", 
        "rate": 0, 
        "reason": "Eventual BG 52<125, Snooze BG 52, setting -10.92U/hr", 
        "eventualBG": 52, 
        "recieved": false, 
        "duration": 0, 
        "mealAssist": "Off: Carbs: undefined Boluses: undefined ISF: 25, Target: 130 Deviation: 7 BGI: -8.86", 
        "tick": -6
      }
    }
  }
]