[
  {
    "trend_arrow": "FLAT", 
    "system_time": "2016-06-01T04:51:35", 
    "display_time": "2016-05-31T21:52:54", 
    "glucose": 134
  }, 
  {
    "trend_arrow": "NOT_COMPUTABLE", 
    "system_time": "2016-06-01T04:46:35", 
    "display_time": "2016-05-31T21:47:54", 
    "glucose": 131
  }, 
  {
    "trend_arrow": "NOT_COMPUTABLE", 
    "system_time": "2016-06-01T04:41:35", 
    "display_time": "2016-05-31T21:42:54", 
    "glucose": 129
  }, 
  {
    "trend_arrow": "NOT_COMPUTABLE", 
    "system_time": "2016-06-01T04:36:35", 
    "display_time": "2016-05-31T21:37:54", 
    "glucose": 125
  }, 
  {
    "trend_arrow": "NOT_COMPUTABLE", 
    "system_time": "2016-06-01T04:31:35", 
    "display_time": "2016-05-31T21:32:54", 
    "glucose": 117
  }
]